README
setup.py
valstream/__init__.py
valstream/dbi.py
valstream/ds.py
valstream/dynamic.py
valstream/graph.py
valstream/io.py
valstream/jss.py
valstream/panya.py
valstream/propify.py
valstream/slow.py
valstream/test.py
valstream/tsv.py
valstream.egg-info/PKG-INFO
valstream.egg-info/SOURCES.txt
valstream.egg-info/dependency_links.txt
valstream.egg-info/entry_points.txt
valstream.egg-info/top_level.txt