Metadata-Version: 1.0
Name: valstream
Version: 0.0.6
Summary: Generalization of Unix pipeline to jsonable data
Home-page: https://github.com/tengu/py-valstream
Author: tengu
Author-email: karasuyamatengu@gmail.com
License: LGPL
Platform: UNKNOWN
Classifier: License :: OSI Approved :: GNU Library or Lesser General Public License (LGPL)
Classifier: Environment :: Console
Classifier: Programming Language :: Python
Classifier: Development Status :: 3 - Alpha
Classifier: Intended Audience :: Developers
Classifier: Topic :: Internet :: WWW/HTTP
Classifier: Topic :: Text Processing :: Filters
Classifier: Topic :: Utilities
Classifier: Topic :: Software Development :: Libraries :: Python Modules
